project_main/__init__.py
project_main/main.py
My_Project_Main_Info-0.1.2.dist-info/LICENSE
My_Project_Main_Info-0.1.2.dist-info/METADATA
My_Project_Main_Info-0.1.2.dist-info/WHEEL
My_Project_Main_Info-0.1.2.dist-info/top_level.txt
My_Project_Main_Info-0.1.2.dist-info/RECORD
