Metadata-Version: 2.1
Name: My-Project-Main-Info
Version: 0.1.2
Summary: My Project Main Info
Home-page: https://github.com/rever273/My-Project-Main-Info
Author: Roman Storm
Author-email: eroasd232@gmail.com
Classifier: Programming Language :: Python :: 3.8
Classifier: License :: OSI Approved :: MIT License
Classifier: Operating System :: OS Independent
Requires-Python: >=3.6
License-File: LICENSE
